{"v":"5.9.0","fr":50,"ip":0,"op":268,"w":1080,"h":1920,"nm":"play_v2","ddd":0,"assets":[{"id":"video_0","w":1080,"h":1920,"u":"images/","p":"vid_0.mp4","e":0}],"layers":[{"ddd":0,"ind":1,"ty":9,"nm":"play_v2.mp4","cl":"mp4","refId":"video_0","sr":1,"ks":{"o":{"a":0,"k":100,"ix":11},"r":{"a":0,"k":0,"ix":10},"p":{"a":0,"k":[540,960,0],"ix":2,"l":2},"a":{"a":0,"k":[540,960,0],"ix":1,"l":2},"s":{"a":0,"k":[100,100,100],"ix":6,"l":2}},"ao":0,"ef":[{"ty":5,"nm":"Color Key","np":6,"mn":"ADBE Color Key","ix":1,"en":1,"ef":[{"ty":2,"nm":"Key Color","mn":"ADBE Color Key-0001","ix":1,"v":{"a":0,"k":[0.003921568859,0.40784317255,0.776470661163,1],"ix":1}},{"ty":0,"nm":"Color Tolerance","mn":"ADBE Color Key-0002","ix":2,"v":{"a":0,"k":45,"ix":2}},{"ty":0,"nm":"Edge Thin","mn":"ADBE Color Key-0003","ix":3,"v":{"a":0,"k":2,"ix":3}},{"ty":0,"nm":"Edge Feather","mn":"ADBE Color Key-0004","ix":4,"v":{"a":0,"k":3.1,"ix":4}}]}],"ip":0,"op":268,"st":-1,"bm":0}],"markers":[]}